spidy/__init__.py
spidy/crawler.py
spidy/gui.py
spidy/tests.py
spidy/config/blank.cfg
spidy/config/default.cfg
spidy/config/docker.cfg
spidy/config/heavy.cfg
spidy/config/infinite.cfg
spidy/config/light.cfg
spidy/config/multithreaded.cfg
spidy/config/rivermont-infinite.cfg
spidy/config/rivermont.cfg
spidy/config/wsj.cfg
spidy/docs/CONTRIBUTING.md
spidy/docs/DOCS.md
spidy_web_crawler-1.6.5.dist-info/DESCRIPTION.rst
spidy_web_crawler-1.6.5.dist-info/METADATA
spidy_web_crawler-1.6.5.dist-info/RECORD
spidy_web_crawler-1.6.5.dist-info/WHEEL
spidy_web_crawler-1.6.5.dist-info/entry_points.txt
spidy_web_crawler-1.6.5.dist-info/metadata.json
spidy_web_crawler-1.6.5.dist-info/top_level.txt
