Metadata-Version: 2.0
Name: spidy-web-crawler
Version: 1.6.5
Summary: Spidy is the simple, easy to use command line web crawler.
Home-page: https://github.com/rivermont/spidy
Author: Will Bennett
Author-email: william.11bennett@gmail.com
License: GPLv3
Keywords: crawler,web crawler,spider,web-spider
Platform: UNKNOWN
Classifier: Development Status :: 5 - Production/Stable
Classifier: Intended Audience :: Developers
Classifier: Intended Audience :: Science/Research
Classifier: License :: OSI Approved :: GNU General Public License v3 (GPLv3)
Classifier: Operating System :: OS Independent
Classifier: Operating System :: Microsoft :: Windows
Classifier: Operating System :: POSIX :: Linux
Classifier: Operating System :: MacOS
Classifier: Environment :: Console
Classifier: Natural Language :: English
Classifier: Programming Language :: Python
Classifier: Programming Language :: Python :: 3
Classifier: Programming Language :: Python :: 3.3
Classifier: Programming Language :: Python :: 3.4
Classifier: Programming Language :: Python :: 3.5
Classifier: Programming Language :: Python :: 3.6
Classifier: Topic :: Internet
Classifier: Topic :: Internet :: WWW/HTTP
Classifier: Topic :: Internet :: WWW/HTTP :: Indexing/Search
Requires-Python: >=3.3
Requires-Dist: requests
Requires-Dist: lxml
Requires-Dist: flake8
Requires-Dist: reppy
